potluckDelivery.py
potluck/__init__.py
potluck/_version.py
potluck/compare.py
potluck/context_utils.py
potluck/contexts.py
potluck/control.py
potluck/default_config.py
potluck/explain.py
potluck/file_utils.py
potluck/harness.py
potluck/html_tools.py
potluck/load.py
potluck/logging.py
potluck/mast.py
potluck/mast_utils.py
potluck/meta.py
potluck/patterns.py
potluck/phrasing.py
potluck/render.py
potluck/rubrics.py
potluck/snippets.py
potluck/specifications.py
potluck/time_utils.py
potluck/timeout.py
potluck/validation.py
potluck/resources/potluck.css
potluck/resources/potluck.js
potluck/templates/instructions.j2
potluck/templates/report.j2
potluck/templates/rubric.j2
potluck/templates/standalone_instructions.j2
potluck/templates/standalone_report.j2
potluck/templates/standalone_tests_report.j2
potluck/templates/tests_report.j2
potluck/testarea/test_course/fall2021/potluck-admin.json
potluck/testarea/test_course/fall2021/potluck_config.py
potluck/testarea/test_course/fall2021/self_printed_mast.py
potluck/testarea/test_course/fall2021/tasks.json
potluck/testarea/test_course/fall2021/examples/imperfect/debugTest/debugMe.py
potluck/testarea/test_course/fall2021/examples/imperfect/debugTest/test_debugMe.py
potluck/testarea/test_course/fall2021/examples/imperfect/filesTest/files.py
potluck/testarea/test_course/fall2021/examples/imperfect/freedomTest/free.py
potluck/testarea/test_course/fall2021/examples/imperfect/functionsTest/functions.py
potluck/testarea/test_course/fall2021/examples/imperfect/functionsTest/test_functions.py
potluck/testarea/test_course/fall2021/examples/imperfect/interactiveTest/interactive.py
potluck/testarea/test_course/fall2021/examples/imperfect/sceneTest/scene.py
potluck/testarea/test_course/fall2021/examples/imperfect/snippetsTest/process.py
potluck/testarea/test_course/fall2021/examples/imperfect/synthTest/arpeggio.py
potluck/testarea/test_course/fall2021/examples/imperfect/synthTest/test_arpeggio.py
potluck_eval-1.2.36.dist-info/LICENSE.txt
potluck_eval-1.2.36.dist-info/METADATA
potluck_eval-1.2.36.dist-info/WHEEL
potluck_eval-1.2.36.dist-info/top_level.txt
potluck_eval-1.2.36.dist-info/RECORD
