Metadata-Version: 2.2
Name: potluck-eval
Version: 1.2.36
Summary: Python code evaluation system and submissions server capable of unit tests, tracing, and AST inspection. Server can run on Python 2.7 but evaluation requires 3.7+.
Home-page: https://cs.wellesley.edu/~pmwh/potluck/docs/
Author: Peter Mawhorter
Author-email: pmawhort@wellesley.edu
License: BSD 3-Clause License
Classifier: Programming Language :: Python :: 3 :: Only
Classifier: Development Status :: 4 - Beta
Classifier: Environment :: Console
Classifier: Framework :: Flask
Classifier: Intended Audience :: Education
Classifier: Intended Audience :: Developers
Classifier: License :: OSI Approved :: BSD License
Classifier: Natural Language :: English
Classifier: Operating System :: OS Independent
Classifier: Topic :: Education
Requires: jinja2
Requires: pygments
Requires: markdown
Requires: beautifulsoup4
Requires: importlib_resources
Requires: python_dateutil
Provides: potluck
Provides: potluck_server
Requires-Python: >=2.7
License-File: LICENSE.txt
Requires-Dist: jinja2
Requires-Dist: pygments
Requires-Dist: markdown
Requires-Dist: beautifulsoup4
Requires-Dist: importlib_resources
Requires-Dist: python_dateutil
Provides-Extra: test
Requires-Dist: pytest; extra == "test"
Provides-Extra: expectations
Requires-Dist: optimism>=2.7.5; extra == "expectations"
Provides-Extra: turtle-capture
Requires-Dist: Pillow>=6.0.0; extra == "turtle-capture"
Provides-Extra: synth
Requires-Dist: wavesynth>=1.0.3; extra == "synth"
Provides-Extra: server
Requires-Dist: flask; extra == "server"
Requires-Dist: flask_cas; extra == "server"
Requires-Dist: redis; extra == "server"
Provides-Extra: security
Requires-Dist: flask_talisman; extra == "security"
Requires-Dist: flask_seasurf; extra == "security"
Provides-Extra: https-debug
Requires-Dist: pyopenssl; extra == "https-debug"
Provides-Extra: formatting
Requires-Dist: pymdown-extensions; extra == "formatting"
Provides-Extra: all
Requires-Dist: pytest; extra == "all"
Requires-Dist: optimism>=2.7.5; extra == "all"
Requires-Dist: Pillow>=6.0.0; extra == "all"
Requires-Dist: wavesynth>=1.0.3; extra == "all"
Requires-Dist: flask; extra == "all"
Requires-Dist: flask_cas; extra == "all"
Requires-Dist: redis; extra == "all"
Requires-Dist: flask_talisman; extra == "all"
Requires-Dist: flask_seasurf; extra == "all"
Requires-Dist: pyopenssl; extra == "all"
Requires-Dist: pymdown-extensions; extra == "all"
Dynamic: author
Dynamic: author-email
Dynamic: classifier
Dynamic: description
Dynamic: description-content-type
Dynamic: home-page
Dynamic: license
Dynamic: provides
Dynamic: provides-extra
Dynamic: requires
Dynamic: requires-dist
Dynamic: requires-python
Dynamic: summary
